WebRiskTester/__init__.py
WebRiskTester/eip.py
WebRiskTester/lgx_comm.py
WebRiskTester/lgx_device.py
WebRiskTester/lgx_response.py
WebRiskTester/lgx_tag.py
WebRiskTester-0.0.1.dist-info/METADATA
WebRiskTester-0.0.1.dist-info/WHEEL
WebRiskTester-0.0.1.dist-info/top_level.txt
WebRiskTester-0.0.1.dist-info/RECORD
