Metadata-Version: 2.1
Name: WebRiskTester
Version: 0.0.1
Summary: Package to test WebRisk API
Author: T
